hyp_client/__init__.py
hyp_client/v1.py
hyp_python_client-0.0.5.dist-info/LICENSE
hyp_python_client-0.0.5.dist-info/METADATA
hyp_python_client-0.0.5.dist-info/WHEEL
hyp_python_client-0.0.5.dist-info/top_level.txt
hyp_python_client-0.0.5.dist-info/RECORD
