Metadata-Version: 2.1
Name: hyp-python-client
Version: 0.0.5
Summary: API client for Hyp
Home-page: https://github.com/Murphydbuffalo/hyp_python_client/
Author: Dan Murphy
Author-email: dan@onhyp.com
Project-URL: Bug Tracker, https://github.com/Murphydbuffalo/hyp_python_client/issues
Classifier: Programming Language :: Python :: 3
Classifier: License :: OSI Approved :: MIT License
Classifier: Operating System :: OS Independent
Requires-Python: >=3.6
License-File: LICENSE
